{
	"_id" : ObjectId("59f2c4dc5bfbda0824dae74a"),
	"images_url" : [
		"http://p3.pstatp.com/origin/37e7000066e72563291d",
		"http://p1.pstatp.com/origin/37e8000040f04be46c23",
		"http://p3.pstatp.com/origin/37e8000040f1aa4cbcdf",
		"http://p3.pstatp.com/origin/37de000247f6b7b52d1a",
		"http://p1.pstatp.com/origin/37e7000066e68332e016",
		"http://p1.pstatp.com/origin/37e5000249581911a60e",
		"http://p1.pstatp.com/origin/37e7000066e84170b0ac"
	],
	"title" : "胡歌是你喜欢的菜吗？",
	"url" : "http://toutiao.com/group/6460190662938591758/"
},
{
	"_id" : ObjectId("59f2c4dc5bfbda362ce3fe57"),
	"images_url" : [
		"http://p1.pstatp.com/origin/3c5d000124a68aa6ebcb",
		"http://p3.pstatp.com/origin/3c5d0001242f7a1851be",
		"http://p1.pstatp.com/origin/3b190002bd8e3a29b84a",
		"http://p1.pstatp.com/origin/3c5b0002b0a4b2e245fa",
		"http://p3.pstatp.com/origin/3b190002bd9ff4537551",
		"http://p9.pstatp.com/origin/3c5e0001142a9b4f27b0",
		"http://p3.pstatp.com/origin/3c5e0001143ce507bf46",
		"http://p3.pstatp.com/origin/3c5a0002b8a9b19cafee",
		"http://p1.pstatp.com/origin/3c5b0002b0dae69382fb",
		"http://p9.pstatp.com/origin/3c5e0001146176dd2a5c",
		"http://p3.pstatp.com/origin/3c5c0002982c42217344",
		"http://p3.pstatp.com/origin/3c5e0001164ff64f0da9",
		"http://p3.pstatp.com/origin/3c5d00012670b6d87df2",
		"http://p1.pstatp.com/origin/3c5a0002bae637a09a77"
	],
	"title" : "胡歌护卫队，干了这杯恒河水",
	"url" : "http://toutiao.com/group/6468975807862669838/"
},
{
	"_id" : ObjectId("59f2c4dc5bfbda3004aa51a3"),
	"images_url" : [
		"http://p1.pstatp.com/origin/43310002240da688f5d9",
		"http://p3.pstatp.com/origin/4334000202ba8cd31389",
		"http://p3.pstatp.com/origin/4330000462f1c19d0b4c",
		"http://p1.pstatp.com/origin/43350001f9057311d07c",
		"http://p3.pstatp.com/origin/4334000202bf6193f849",
		"http://p1.pstatp.com/origin/4336000080514b8ed3b0",
		"http://p3.pstatp.com/origin/4333000210cd24318564",
		"http://p1.pstatp.com/origin/4334000202c6c76ba519",
		"http://p3.pstatp.com/origin/4334000202c8114a5661"
	],
	"title" : "胡歌和吴磊的时尚大片，一个让我恨自己晚生十年，一个早生十年",
	"url" : "http://toutiao.com/group/6481221614074593806/"
},
{
	"_id" : ObjectId("59f2c4df5bfbda3004aa51a4"),
	"images_url" : [
		"http://p1.pstatp.com/origin/37e70002b6559b55311e",
		"http://p3.pstatp.com/origin/37e4000498e72313d8c0",
		"http://p9.pstatp.com/origin/37e4000498e96af72fd2",
		"http://p3.pstatp.com/origin/37e4000498ea3773f924",
		"http://p3.pstatp.com/origin/37e60004875713a1f0f1",
		"http://p3.pstatp.com/origin/37e4000498ef36fc8f6f"
	],
	"title" : "脱下正装，老干部胡歌变身活力帅小伙",
	"url" : "http://toutiao.com/group/6460369909900640781/"
},
{
	"_id" : ObjectId("59f2c4e05bfbda3b5429773e"),
	"images_url" : [
		"http://p3.pstatp.com/origin/39ba0003b003eb3605e7",
		"http://p1.pstatp.com/origin/39bd000222beadd29f9c",
		"http://p3.pstatp.com/origin/39bb0003ac762b34cbef",
		"http://p3.pstatp.com/origin/39bd0002255f243b29ec",
		"http://p1.pstatp.com/origin/39bc0003a4e5536e7cf9",
		"http://p9.pstatp.com/origin/39b90003c89df775f4de"
	],
	"title" : "胡歌夜会神秘女子，有情况",
	"url" : "http://toutiao.com/group/6464411083560976910/"
},
{
	"_id" : ObjectId("59f2c4e05bfbda362ce3fe58"),
	"images_url" : [
		"http://p3.pstatp.com/origin/3a0600014fc7699d1d99",
		"http://p3.pstatp.com/origin/3a04000498b389549c7b",
		"http://p3.pstatp.com/origin/3a0700013fc83f1750e5",
		"http://p3.pstatp.com/origin/3a080001509f97349912",
		"http://p3.pstatp.com/origin/3a09000124035d36dfd3"
	],
	"title" : "胡歌的简单生活，去繁存简，优雅惬意",
	"url" : "http://toutiao.com/group/6465880127216550414/"
},
{
	"_id" : ObjectId("59f2c4e15bfbda0824dae74b"),
	"images_url" : [
		"http://p3.pstatp.com/origin/402c00037ccacd218d9d",
		"http://p3.pstatp.com/origin/402b000385617e13b0b0",
		"http://p3.pstatp.com/origin/402b000385e49352fa2c",
		"http://p3.pstatp.com/origin/402f000216673fb76d42",
		"http://p3.pstatp.com/origin/402a00038f2e6868f799",
		"http://p1.pstatp.com/origin/402d0003737c73a04f57",
		"http://p1.pstatp.com/origin/402a00038f5c294f6e09",
		"http://p1.pstatp.com/origin/402d000373a9eb40f456",
		"http://p3.pstatp.com/origin/402e00036a40f91484bd"
	],
	"title" : "九流：胡歌",
	"url" : "http://toutiao.com/group/6479671952150626829/"
},
{
	"_id" : ObjectId("59f2c4e45bfbda0824dae74c"),
	"images_url" : [
		"http://p1.pstatp.com/origin/3b0b0000f3ba31921751",
		"http://p1.pstatp.com/origin/3b0d0000f03f5e1ae6e1",
		"http://p3.pstatp.com/origin/3b0900040ee705bcd6c3",
		"http://p3.pstatp.com/origin/3b0d0000f0406fa84569",
		"http://p1.pstatp.com/origin/3b0a0000f9e12e1d1ca1",
		"http://p3.pstatp.com/origin/3b0a0000f9e3c96328ec",
		"http://p1.pstatp.com/origin/3b0d0000f0422b0116a1",
		"http://p3.pstatp.com/origin/3b0900040eec20597a4c",
		"http://p1.pstatp.com/origin/3b0e0000da9ebe9d174e"
	],
	"title" : "猜猜看胡歌这些古装角色都出自哪？",
	"url" : "http://toutiao.com/group/6467683832375034381/"
},
{
	"_id" : ObjectId("59f2c4e55bfbda3004aa51a5"),
	"images_url" : [
		"http://p3.pstatp.com/origin/321a000489d04bf89622",
		"http://p3.pstatp.com/origin/32120003a144093ff0cc",
		"http://p1.pstatp.com/origin/320a0004f118c962070c",
		"http://p3.pstatp.com/origin/322b00035da610ed9534",
		"http://p1.pstatp.com/origin/322b00035e93f8ce7c2d"
	],
	"title" : "胡歌早年拍过的影片",
	"url" : "http://toutiao.com/group/6454491219971015181/"
},
{
	"_id" : ObjectId("59f2c4e65bfbda3004aa51a6"),
	"images_url" : [
		"http://p3.pstatp.com/origin/3b1500031eb3accad340",
		"http://p3.pstatp.com/origin/3b1100032b4f6b681506",
		"http://p9.pstatp.com/origin/3b160002fcdb39b09b2c",
		"http://p1.pstatp.com/origin/3b1200032955f9428351"
	],
	"title" : "为救胡歌离世，胡歌以她名义捐30所学校；网友：世上最好的胡歌",
	"url" : "http://toutiao.com/group/6468452021589508622/"
},
{
	"_id" : ObjectId("59f2c4e65bfbda3b5429773f"),
	"images_url" : [
		"http://p1.pstatp.com/origin/433000033f5c41c227a2",
		"http://p1.pstatp.com/origin/43300003602b1601274b",
		"http://p3.pstatp.com/origin/43350000d5d358ae0811",
		"http://p9.pstatp.com/origin/43320000f3fab5c3863c",
		"http://p3.pstatp.com/origin/43330000eb6421c5e914",
		"http://p1.pstatp.com/origin/43340000df1d487e5d42",
		"http://p1.pstatp.com/origin/43350000d5c0c604ca68",
		"http://p3.pstatp.com/origin/43320000f3f65c1b0339",
		"http://p1.pstatp.com/origin/4332000128f785f937e9",
		"http://p3.pstatp.com/origin/432f00040dfd08351883",
		"http://p3.pstatp.com/origin/43310000ff14f8e20cf6"
	],
	"title" : "为省钱捡剩饭吃，16岁独自扛起家庭巨债，胡歌、陈柏霖都为之动容",
	"url" : "http://toutiao.com/group/6481139295863177741/"
},
{
	"_id" : ObjectId("59f2c4e75bfbda362ce3fe59"),
	"images_url" : [
		"http://p3.pstatp.com/origin/39a70004877e2ab1f502",
		"http://p3.pstatp.com/origin/39a500048aedd7905df0",
		"http://p9.pstatp.com/origin/39a600048b499f763c31",
		"http://p3.pstatp.com/origin/39a90002969fe18ed44b",
		"http://p3.pstatp.com/origin/39a9000296a24f68a66a",
		"http://p1.pstatp.com/origin/39a400049612022c305e",
		"http://p1.pstatp.com/origin/39a30004987e5aa929aa",
		"http://p3.pstatp.com/origin/39a400049615d2eecfa8",
		"http://p9.pstatp.com/origin/39a800027b643aa38ba8",
		"http://p3.pstatp.com/origin/39a800027b694f95df37",
		"http://p3.pstatp.com/origin/39a800027b6b5d20886a",
		"http://p3.pstatp.com/origin/39a70004877f97f02a4c"
	],
	"title" : "看看胡歌征服过的发型，款款帅",
	"url" : "http://toutiao.com/group/6462537450144137742/"
},
{
	"_id" : ObjectId("59f2c4e95bfbda3b54297740"),
	"images_url" : [
		"http://p3.pstatp.com/origin/3f2a00006b1e54ee03d1",
		"http://p3.pstatp.com/origin/3f2500037a775bb85e0a",
		"http://p3.pstatp.com/origin/3f2500037a792c2a115f",
		"http://p3.pstatp.com/origin/3f2800006ccd330e156d"
	],
	"title" : "胡歌最新帅气图集，这个胡歌痞气十足哦",
	"url" : "http://toutiao.com/group/6475794357189345805/"
},
{
	"_id" : ObjectId("59f2c4eb5bfbda3004aa51a7"),
	"images_url" : [
		"http://p3.pstatp.com/origin/43320001d27cdfcb6f4a",
		"http://p1.pstatp.com/origin/4336000038fd190ce158",
		"http://p3.pstatp.com/origin/43310001dd10ac0a79bd",
		"http://p1.pstatp.com/origin/43330001c92c6354da4c",
		"http://p3.pstatp.com/origin/43310001dd1699fcc3dd"
	],
	"title" : "盘点都是在上海出生的男星，网友：个个都有才华，有演技！",
	"url" : "http://toutiao.com/group/6481200475768095246/"
},
{
	"_id" : ObjectId("59f2c4eb5bfbda0824dae74d"),
	"images_url" : [
		"http://p3.pstatp.com/origin/39a30003021c80227189",
		"http://p1.pstatp.com/origin/39a300030222717ecd49",
		"http://p3.pstatp.com/origin/39a80000e4454d688e4a",
		"http://p3.pstatp.com/origin/39a40002fdfff69f00ba",
		"http://p1.pstatp.com/origin/39a80000e45230e50c86",
		"http://p3.pstatp.com/origin/39a40002fe23b8318d21",
		"http://p9.pstatp.com/origin/39a300030499b2c6a1f3",
		"http://p1.pstatp.com/origin/39a60002f71ca49ee6cd"
	],
	"title" : "一张图诠释胡歌的影视圈的精彩",
	"url" : "http://toutiao.com/group/6462288859181875726/"
},
{
	"_id" : ObjectId("59f2c4ef5bfbda362ce3fe5a"),
	"images_url" : [
		"http://p1.pstatp.com/origin/3a0400038d1be47fc8bd",
		"http://p1.pstatp.com/origin/3a08000040fcb8208f9c",
		"http://p3.pstatp.com/origin/3a06000045354fd2bf16",
		"http://p3.pstatp.com/origin/3a07000031df2f317135",
		"http://p1.pstatp.com/origin/3a0500004adf842f26fd",
		"http://p1.pstatp.com/origin/3a08000041175cf0c4d5",
		"http://p1.pstatp.com/origin/3a0400038d3848021c13",
		"http://p3.pstatp.com/origin/3a07000031fa85651b2f"
	],
	"title" : "明星图集：帅气的胡歌",
	"url" : "http://toutiao.com/group/6465806581375173134/"
},
{
	"_id" : ObjectId("59f2c4f15bfbda362ce3fe5b"),
	"images_url" : [
		"http://p1.pstatp.com/origin/3c62000296827d945076",
		"http://p1.pstatp.com/origin/3c6200029683ebaa7bc3",
		"http://p1.pstatp.com/origin/3c600002a3baabdfa68f",
		"http://p1.pstatp.com/origin/3c640000eba523010b26"
	],
	"title" : "短发的胡歌帅气归来",
	"url" : "http://toutiao.com/group/6469607949797949966/"
},
{
	"_id" : ObjectId("59f2c4f15bfbda3b54297741"),
	"images_url" : [
		"http://p1.pstatp.com/origin/3eb2000165ff76b14a75",
		"http://p3.pstatp.com/origin/3eb2000166009289d33f",
		"http://p9.pstatp.com/origin/3e670002f32e03b3a1b1",
		"http://p3.pstatp.com/origin/3e690002e98eda75d1ad",
		"http://p1.pstatp.com/origin/3eb200016601044fb7e4",
		"http://p9.pstatp.com/origin/3e690002e99160c5a340",
		"http://p3.pstatp.com/origin/3e6b0002c1cb1769cd73",
		"http://p3.pstatp.com/origin/3e6b0002c1cd189f0a9a",
		"http://p3.pstatp.com/origin/3e690002e995b337072f"
	],
	"title" : "阿一吕：有味道的胡歌",
	"url" : "http://toutiao.com/group/6474501910886875661/"
},
{
	"_id" : ObjectId("59f2c4f35bfbda3b54297742"),
	"images_url" : [
		"http://p1.pstatp.com/origin/401b00000b1f713da963",
		"http://p3.pstatp.com/origin/401500043ebd91079dde",
		"http://p3.pstatp.com/origin/401500043ebeccc883cd",
		"http://p3.pstatp.com/origin/40180001ae003e7269dc",
		"http://p3.pstatp.com/origin/4017000188a5d1e6980c",
		"http://p1.pstatp.com/origin/401900018a16a0b60ff1",
		"http://p1.pstatp.com/origin/401200018a90d27076a4",
		"http://p3.pstatp.com/origin/401b00000b2ca2605193"
	],
	"title" : "人气演员胡歌帅气西装照",
	"url" : "http://toutiao.com/group/6477893234977669646/"
},
{
	"_id" : ObjectId("59f2c4f45bfbda3004aa51a8"),
	"images_url" : [
		"http://p1.pstatp.com/origin/40430003f66cde067e40",
		"http://p3.pstatp.com/origin/403c00040ec8ba5df764",
		"http://p3.pstatp.com/origin/404100041a0f182d16bf",
		"http://p1.pstatp.com/origin/43300002006b8e20615b",
		"http://p3.pstatp.com/origin/4042000406a9eecc51fd",
		"http://p3.pstatp.com/origin/4041000419e990eba227"
	],
	"title" : "6对明星情侣，第2对“男闺蜜”打败胡歌上位！",
	"url" : "http://toutiao.com/group/6481077496400839182/"
},
{
	"_id" : ObjectId("59f2c4f55bfbda0824dae74e"),
	"images_url" : [
		"http://p3.pstatp.com/origin/3c6c0002487d62e90559",
		"http://p1.pstatp.com/origin/3c6700042fca3c184f08",
		"http://p9.pstatp.com/origin/3c6c000248a2aba4679e",
		"http://p3.pstatp.com/origin/3c6900042720b4314d0b",
		"http://p1.pstatp.com/origin/3c69000427232f2bf0bc",
		"http://p1.pstatp.com/origin/3c6b000429f151f3b370",
		"http://p1.pstatp.com/origin/3c6500024c5577d82500",
		"http://p3.pstatp.com/origin/3c68000428da0f2c18d9"
	],
	"title" : "明星图集：刘诗诗 胡歌",
	"url" : "http://toutiao.com/group/6470275561611592206/"
},
{
	"_id" : ObjectId("59f2c4f65bfbda3004aa51a9"),
	"images_url" : [
		"http://p1.pstatp.com/origin/3afb0003735ff0f39010",
		"http://p3.pstatp.com/origin/3afd000083d3a97ab7be",
		"http://p3.pstatp.com/origin/3afd000083d4164acb9a",
		"http://p3.pstatp.com/origin/3aff00007178b7b8d066",
		"http://p1.pstatp.com/origin/3afc00008575c2120297",
		"http://p3.pstatp.com/origin/3afe000072cba1762b98",
		"http://p9.pstatp.com/origin/3afb00037361cdabaaa0",
		"http://p3.pstatp.com/origin/3afd000083d8d0786077",
		"http://p3.pstatp.com/origin/3b0000005b24a15473bc"
	],
	"title" : "这样子的胡歌 你喜欢吗",
	"url" : "http://toutiao.com/group/6466373685132395021/"
},
{
	"_id" : ObjectId("59f2c4f95bfbda362ce3fe5c"),
	"images_url" : [
		"http://p1.pstatp.com/origin/39fb0004e2d3e5d7da2e",
		"http://p9.pstatp.com/origin/39f70004f7613d6f6d27",
		"http://p3.pstatp.com/origin/39fe0002fd0647f3a96c",
		"http://p1.pstatp.com/origin/39fe0002fd09628ce65c",
		"http://p3.pstatp.com/origin/39fc0004d570d947e797",
		"http://p3.pstatp.com/origin/39fc0004d5729ecb5cbf",
		"http://p3.pstatp.com/origin/39f90004e7228377d9a7",
		"http://p3.pstatp.com/origin/39f70004f7741c7e41a8",
		"http://p3.pstatp.com/origin/39f70004f77e257fb3e7",
		"http://p1.pstatp.com/origin/39fd000311a664e5f999"
	],
	"title" : "胡歌帅气写真集，你更喜欢哪一张？",
	"url" : "http://toutiao.com/group/6465115474211373581/"
},
{
	"_id" : ObjectId("59f2c4f95bfbda3004aa51aa"),
	"images_url" : [
		"http://p9.pstatp.com/origin/31fa00014a61388a265b",
		"http://p9.pstatp.com/origin/320700025dd16ba3fee4",
		"http://p3.pstatp.com/origin/31f60002ae37d72969de",
		"http://p3.pstatp.com/origin/31fa00014a740933efcf"
	],
	"title" : "明星图集：胡歌帅气成熟男人胡歌不一样的风采",
	"url" : "http://toutiao.com/group/6452926151034667534/"
},
{
	"_id" : ObjectId("59f2c4fa5bfbda3b54297743"),
	"images_url" : [
		"http://p3.pstatp.com/origin/321b0001e418eeeeade1",
		"http://p3.pstatp.com/origin/32100000d4febd996263",
		"http://p9.pstatp.com/origin/322d00003628f85fecc1",
		"http://p3.pstatp.com/origin/322a000341d717ce0d07",
		"http://p1.pstatp.com/origin/322a000341d8cf7e41b2",
		"http://p3.pstatp.com/origin/321b0001e427e8ae5637",
		"http://p1.pstatp.com/origin/32100000d506142f3bc7",
		"http://p3.pstatp.com/origin/32100000d507abd1c33c"
	],
	"title" : "胡歌魅力男神舔屏帅哥手机锁屏壁纸",
	"url" : "http://toutiao.com/group/6454757954674491917/"
},
{
	"_id" : ObjectId("59f2c4fb5bfbda0824dae74f"),
	"images_url" : [
		"http://p3.pstatp.com/origin/31fe000250343cd7fa29",
		"http://p1.pstatp.com/origin/320600019526ef79f88d",
		"http://p3.pstatp.com/origin/3202000250430e57d666",
		"http://p1.pstatp.com/origin/31fe000250390f973d8e",
		"http://p3.pstatp.com/origin/31f5000405b34e3f0429",
		"http://p1.pstatp.com/origin/31f700025e24c71a2c2e",
		"http://p9.pstatp.com/origin/3211000195d32c487640",
		"http://p1.pstatp.com/origin/31f5000405b968e20831",
		"http://p9.pstatp.com/origin/31f5000405baa6605a6c",
		"http://p1.pstatp.com/origin/31f5000405bfa82eb36f",
		"http://p1.pstatp.com/origin/3211000195db071033f7",
		"http://p3.pstatp.com/origin/31f5000405c5ea6d765d",
		"http://p3.pstatp.com/origin/31fe0002504698dd23f8",
		"http://p3.pstatp.com/origin/31f5000405c932ef20c6",
		"http://p3.pstatp.com/origin/3211000195e693d55140",
		"http://p3.pstatp.com/origin/31fe0002504bd086b049"
	],
	"title" : "你们的老公胡歌来了",
	"url" : "http://toutiao.com/group/6452472018590761486/"
},
{
	"_id" : ObjectId("59f2c4fc5bfbda3b54297744"),
	"images_url" : [
		"http://p3.pstatp.com/origin/31fb0001fda515bb420b",
		"http://p1.pstatp.com/origin/32170001394c5f072e37",
		"http://p3.pstatp.com/origin/31fb0001fc0f03d52c92",
		"http://p1.pstatp.com/origin/321e0000b713424d298d",
		"http://p3.pstatp.com/origin/320300023e619aa60bec"
	],
	"title" : "靳东与江疏影捏脸恶搞，网友：胡歌看不下去了！",
	"url" : "http://toutiao.com/group/6453600713627927053/"
},
{
	"_id" : ObjectId("59f2c4ff5bfbda0824dae750"),
	"images_url" : [
		"http://p1.pstatp.com/origin/31ed000233bc36a27104",
		"http://p3.pstatp.com/origin/31f0000231f197e96689",
		"http://p3.pstatp.com/origin/31f0000231f6e18b0ba8",
		"http://p9.pstatp.com/origin/31eb00047c75b8d076ad",
		"http://p3.pstatp.com/origin/31ed000233d0455d6d15",
		"http://p1.pstatp.com/origin/31e900039c4dab9fd715",
		"http://p9.pstatp.com/origin/31f40003bf10d5687662",
		"http://p3.pstatp.com/origin/31e600047a0fc43f3346"
	],
	"title" : "胡歌｜成长与受伤都是猝不及防",
	"url" : "http://toutiao.com/group/6451313770346135821/"
},
{
	"_id" : ObjectId("59f2c5015bfbda3004aa51ab"),
	"images_url" : [
		"http://p1.pstatp.com/origin/242a00010a17267f1892",
		"http://p9.pstatp.com/origin/22d900044e4064293324",
		"http://p1.pstatp.com/origin/242b000047283cfa426e",
		"http://p9.pstatp.com/origin/242b000048f20c9542cd",
		"http://p1.pstatp.com/origin/242b000047533a6c14f3",
		"http://p3.pstatp.com/origin/22d80004578f0393c9f6",
		"http://p3.pstatp.com/origin/242a00010baf3cfca352"
	],
	"title" : "这6个角色，胡歌之后，无人超越！",
	"url" : "http://toutiao.com/group/6426309222104203521/"
},
{
	"_id" : ObjectId("59f2c5015bfbda0824dae751"),
	"images_url" : [
		"http://p9.pstatp.com/origin/ba40004c8e6d391d042",
		"http://p3.pstatp.com/origin/ba20004c7f42c4a4db9",
		"http://p3.pstatp.com/origin/ba30004c904e8753900",
		"http://p3.pstatp.com/origin/b9d00057cc9431577a0"
	],
	"title" : "网友和胡歌同航班，胡歌戴礼帽，坐头等舱",
	"url" : "http://toutiao.com/group/6314624910690386178/"
},
{
	"_id" : ObjectId("59f2c5035bfbda0824dae752"),
	"images_url" : [
		"http://p3.pstatp.com/origin/243a000192f061834244",
		"http://p1.pstatp.com/origin/2434000177812c6e23fc",
		"http://p9.pstatp.com/origin/243700059015c9c86e19",
		"http://p9.pstatp.com/origin/243900025d04f1756a41",
		"http://p3.pstatp.com/origin/24350005ccfed3d40950"
	],
	"title" : "胡歌曝光硬汉照，胸前纹身抢镜",
	"url" : "http://toutiao.com/group/6428527951676260610/"
},
{
	"_id" : ObjectId("59f2c5055bfbda3b54297745"),
	"images_url" : [
		"http://p1.pstatp.com/origin/4331000219d4f12775a6",
		"http://p3.pstatp.com/origin/433200020f3cb5250627",
		"http://p3.pstatp.com/origin/4336000075c7878df8cf",
		"http://p3.pstatp.com/origin/43340001f87fa1903fb2",
		"http://p9.pstatp.com/origin/4336000075ce9ef9e1e4",
		"http://p3.pstatp.com/origin/433200020f45037d191d",
		"http://p3.pstatp.com/origin/43340001f88225462ca8",
		"http://p9.pstatp.com/origin/4333000206068d94deb4",
		"http://p3.pstatp.com/origin/43330002060a3df264b7"
	],
	"title" : "男星穿西服谁更有型？吴尊胡歌很帅气，鹿晗杨洋有点骚包",
	"url" : "http://toutiao.com/group/6481219969689321998/"
},
{
	"_id" : ObjectId("59f2c5075bfbda3b54297746"),
	"images_url" : [
		"http://p3.pstatp.com/origin/37e6000204b273d0e620",
		"http://p3.pstatp.com/origin/37de00020f2edba56017",
		"http://p3.pstatp.com/origin/37e8000008d94bee405a",
		"http://p1.pstatp.com/origin/37e800000968cb81fbf3"
	],
	"title" : "胡歌，成长中的男人",
	"url" : "http://toutiao.com/group/6460083459124625933/"
},
{
	"_id" : ObjectId("59f2c50b5bfbda3004aa51ac"),
	"images_url" : [
		"http://p3.pstatp.com/origin/37f10001890261f14687",
		"http://p3.pstatp.com/origin/37eb0003b95d77404dad",
		"http://p3.pstatp.com/origin/37e90003b947a9300cb8",
		"http://p1.pstatp.com/origin/37f10001890be99ba037",
		"http://p3.pstatp.com/origin/37ef0003a66666512e72",
		"http://p1.pstatp.com/origin/37ea0003a83960a3bff1",
		"http://p3.pstatp.com/origin/37eb0003b974c821114b",
		"http://p1.pstatp.com/origin/37f00001bbbf2a699fd5",
		"http://p3.pstatp.com/origin/37ea0003a83deb08e5e6",
		"http://p3.pstatp.com/origin/37e90003b95d3530ccef",
		"http://p3.pstatp.com/origin/37eb0003b981ca71698b",
		"http://p1.pstatp.com/origin/37eb0003b984313a6220",
		"http://p3.pstatp.com/origin/37ee0003ac2b407ec4b5",
		"http://p3.pstatp.com/origin/37e90003b9622d035170",
		"http://p3.pstatp.com/origin/37ea0003a84b9a370adb",
		"http://p9.pstatp.com/origin/37ef0003aa6be3910da7",
		"http://p1.pstatp.com/origin/37eb0003b95f0205223f",
		"http://p3.pstatp.com/origin/37f00001bbb13eb30d23",
		"http://p1.pstatp.com/origin/37eb0003bdc4f459d433"
	],
	"title" : "胡歌有演技吗？！",
	"url" : "http://toutiao.com/group/6461016918424814094/"
},
{
	"_id" : ObjectId("59f2c50c5bfbda3b54297747"),
	"images_url" : [
		"http://p1.pstatp.com/origin/3a050002061747d257ad",
		"http://p3.pstatp.com/origin/3a090001d7210115e950",
		"http://p1.pstatp.com/origin/3afb000013b295216310",
		"http://p3.pstatp.com/origin/3a090001e552b159c02c",
		"http://p9.pstatp.com/origin/3a090001e86b21e84f77",
		"http://p3.pstatp.com/origin/3a080002193f85ae33fa",
		"http://p9.pstatp.com/origin/3a050002222c85664cfc",
		"http://p1.pstatp.com/origin/3afa000034605e12be3d",
		"http://p3.pstatp.com/origin/3a090001f60e170ca07f",
		"http://p3.pstatp.com/origin/3afa0000397cd987bad7",
		"http://p1.pstatp.com/origin/3a07000217b16f885ce0",
		"http://p1.pstatp.com/origin/3a0700021c50dde16750"
	],
	"title" : "胡歌经典的电视剧，你看过其中哪些？",
	"url" : "http://toutiao.com/group/6465933657000378893/"
},
{
	"_id" : ObjectId("59f2c50e5bfbda362ce3fe5d"),
	"images_url" : [
		"http://p3.pstatp.com/origin/4043000406e39fc1cc2c",
		"http://p3.pstatp.com/origin/403c00041fd69f6bb9af",
		"http://p3.pstatp.com/origin/403c00041fda977e8282",
		"http://p9.pstatp.com/origin/404100042ad8594ae1fe",
		"http://p3.pstatp.com/origin/432f0002a19e800c1873",
		"http://p3.pstatp.com/origin/404000043e015f1541fd",
		"http://p3.pstatp.com/origin/404100042af3ba2fcd71",
		"http://p3.pstatp.com/origin/403c00041ffa4daf49c5",
		"http://p1.pstatp.com/origin/404000043e180dc76179"
	],
	"title" : "《猎场》曝光人物海报 胡歌孙红雷等主创呈现不同的角色风格",
	"url" : "http://toutiao.com/group/6481074095550104077/"
},
{
	"_id" : ObjectId("59f2c5105bfbda3004aa51ad"),
	"images_url" : [
		"http://p1.pstatp.com/origin/37de00053971ebe9f53c",
		"http://p3.pstatp.com/origin/37de00053973ea86d347",
		"http://p3.pstatp.com/origin/37e800033506d814f084",
		"http://p3.pstatp.com/origin/37e60005313e18598205",
		"http://p1.pstatp.com/origin/37de0005397d456b8da2",
		"http://p3.pstatp.com/origin/37e500053a263ee85f5c",
		"http://p3.pstatp.com/origin/37e800033511ad8e06df",
		"http://p1.pstatp.com/origin/37e300054745b320b775"
	],
	"title" : "明星图集：胡歌最新影视剧照 胡歌步入姐弟恋",
	"url" : "http://toutiao.com/group/6460437873274389006/"
},
{
	"_id" : ObjectId("59f2c5135bfbda362ce3fe5e"),
	"images_url" : [
		"http://p3.pstatp.com/origin/37c400016863daf31f30",
		"http://p1.pstatp.com/origin/32210004be02f5b259f1",
		"http://p1.pstatp.com/origin/37c6000169d7becf76e0",
		"http://p1.pstatp.com/origin/37c200016b23888acfba",
		"http://p1.pstatp.com/origin/32210004be271a8c855b",
		"http://p1.pstatp.com/origin/37c200016b37738183f3",
		"http://p1.pstatp.com/origin/32270004b6718830837c"
	],
	"title" : "帅气温暖的胡歌，无可取代，古月与你同在",
	"url" : "http://toutiao.com/group/6456678697335259661/"
},
{
	"_id" : ObjectId("59f2c5135bfbda0824dae753"),
	"images_url" : [
		"http://p1.pstatp.com/origin/f760007c25ac27b8bab",
		"http://p3.pstatp.com/origin/f750007c534b8d0b3bd",
		"http://p3.pstatp.com/origin/f7900055adf12ce7bff",
		"http://p1.pstatp.com/origin/f77000032662fbbfea7",
		"http://p1.pstatp.com/origin/efa0007cc9c491406ec",
		"http://p3.pstatp.com/origin/efa0007cd23fc0dcac8",
		"http://p1.pstatp.com/origin/f750007bf8487e474cf",
		"http://p3.pstatp.com/origin/f730007c6c28bd2ef3d",
		"http://p9.pstatp.com/origin/efa0007cd605a16e635",
		"http://p3.pstatp.com/origin/f79000555a2710d1c41",
		"http://p9.pstatp.com/origin/f760007c358006f2dd5",
		"http://p1.pstatp.com/origin/f730007c723c04e213f",
		"http://p3.pstatp.com/origin/f760007c477e0379fae",
		"http://p1.pstatp.com/origin/f750007c1343e6e15c6",
		"http://p3.pstatp.com/origin/f7900055702884e72bd",
		"http://p3.pstatp.com/origin/f7900055712db83bc2e",
		"http://p3.pstatp.com/origin/f7900055719851737ee",
		"http://p9.pstatp.com/origin/f760007c4d8d42f334a",
		"http://p3.pstatp.com/origin/f750007cb823dffb7ff",
		"http://p3.pstatp.com/origin/efa0007d28025c69121"
	],
	"title" : "胡歌：一个演员的自我修养",
	"url" : "http://toutiao.com/group/6342397691507540226/"
},
{
	"_id" : ObjectId("59f2c5145bfbda3b54297748"),
	"images_url" : [
		"http://p3.pstatp.com/origin/37d2000215371699fd2a",
		"http://p1.pstatp.com/origin/37d20002153435f9a16c",
		"http://p1.pstatp.com/origin/322800001b217298bb67",
		"http://p1.pstatp.com/origin/37ce00022565a2e3b500",
		"http://p9.pstatp.com/origin/37cf00022407e92847d3",
		"http://p3.pstatp.com/origin/37d400002fe268ef3918",
		"http://p1.pstatp.com/origin/37d30002125d07272988",
		"http://p1.pstatp.com/origin/37ce00022541a047c400"
	],
	"title" : "胡歌：最适合穿西装的男人",
	"url" : "http://toutiao.com/group/6458046398817370638/"
},
{
	"_id" : ObjectId("59f2c5145bfbda362ce3fe5f"),
	"images_url" : [
		"http://p1.pstatp.com/origin/31ff00042b40529a79be",
		"http://p3.pstatp.com/origin/31f00003e88b080c77ac",
		"http://p3.pstatp.com/origin/321000002c80fc66ce2c"
	],
	"title" : "胡歌热舞，林更新尴尬了",
	"url" : "http://toutiao.com/group/6452059315518833165/"
},
{
	"_id" : ObjectId("59f2c5165bfbda362ce3fe60"),
	"images_url" : [
		"http://p3.pstatp.com/origin/321e000139f7d159572d",
		"http://p1.pstatp.com/origin/32170001bc9cf01cab29",
		"http://p1.pstatp.com/origin/32170001bc9f358f596b",
		"http://p1.pstatp.com/origin/32170001bca19df5e1e6",
		"http://p3.pstatp.com/origin/3200000147a298d1fb57",
		"http://p1.pstatp.com/origin/321a0001bbdb7c8dec49",
		"http://p3.pstatp.com/origin/32170001bcad778e4388"
	],
	"title" : "一生没有绯闻的男明星-胡歌",
	"url" : "http://toutiao.com/group/6453664127469486606/"
},
{
	"_id" : ObjectId("59f2c5165bfbda0824dae754"),
	"images_url" : [
		"http://p1.pstatp.com/origin/149b00010b38cb293845",
		"http://p3.pstatp.com/origin/149b00010b39823462bf",
		"http://p1.pstatp.com/origin/149f00010b290753dcc4",
		"http://p3.pstatp.com/origin/141d00072ca7071fcfde",
		"http://p1.pstatp.com/origin/149e00036364f15e29ee",
		"http://p9.pstatp.com/origin/149b00010b3e5410a299",
		"http://p3.pstatp.com/origin/149e00036366e1bbf570",
		"http://p1.pstatp.com/origin/141d00072caafe75e65e",
		"http://p3.pstatp.com/origin/141d00072cabadb19f69"
	],
	"title" : "胡歌！大写的帅",
	"url" : "http://toutiao.com/group/6370952916450312450/"
},
{
	"_id" : ObjectId("59f2c5175bfbda3004aa51ae"),
	"images_url" : [
		"http://p1.pstatp.com/origin/3b1100022a89cfcdcf0f",
		"http://p3.pstatp.com/origin/3b170000708c5a7ae1b6",
		"http://p3.pstatp.com/origin/3b160001fc19aecdb0df",
		"http://p3.pstatp.com/origin/3b18000064623616c192",
		"http://p1.pstatp.com/origin/3b1500021ca9d66a9906",
		"http://p3.pstatp.com/origin/3b160001fc1aa898e702",
		"http://p3.pstatp.com/origin/3b1300021c370f07578b",
		"http://p3.pstatp.com/origin/3b1300021c385a0b0e10",
		"http://p3.pstatp.com/origin/3b1100022a8b0aa443dd",
		"http://p3.pstatp.com/origin/3b170000708d6a1f7c08"
	],
	"title" : "胡歌照片大全高清图片 胡歌图片最帅图片",
	"url" : "http://toutiao.com/group/6468373466998374925/"
},
{
	"_id" : ObjectId("59f2c51c5bfbda3b54297749"),
	"images_url" : [
		"http://p1.pstatp.com/origin/37f000043dc4aa7ef4e5",
		"http://p3.pstatp.com/origin/37f2000121e37398b4b3",
		"http://p3.pstatp.com/origin/37ec00011e69f2d69108",
		"http://p3.pstatp.com/origin/37f100040f74be1eb89a",
		"http://p9.pstatp.com/origin/37f000043dc9f985e677",
		"http://p3.pstatp.com/origin/37f3000115d193723b16",
		"http://p3.pstatp.com/origin/37f000043e68f59c08bb"
	],
	"title" : "胡歌，给我一个讨厌他的理由",
	"url" : "http://toutiao.com/group/6461443601338466829/"
},
{
	"_id" : ObjectId("59f2c51d5bfbda362ce3fe61"),
	"images_url" : [
		"http://p3.pstatp.com/origin/3a040000969cba62f035",
		"http://p3.pstatp.com/origin/3a040000969fc0f9a370",
		"http://p3.pstatp.com/origin/3a030000a2add220e445",
		"http://p1.pstatp.com/origin/3a0100027034c5eb2c1b",
		"http://p1.pstatp.com/origin/39ff000284b3a4fabb17",
		"http://p9.pstatp.com/origin/3a010002703b9498bf9b",
		"http://p3.pstatp.com/origin/3a0200025ae4e2b0339e",
		"http://p3.pstatp.com/origin/3a030000a2b9347926f9"
	],
	"title" : "明星图集：霍建华与胡歌",
	"url" : "http://toutiao.com/group/6465450584580293134/"
},
{
	"_id" : ObjectId("59f2c51e5bfbda362ce3fe62"),
	"images_url" : [
		"http://p3.pstatp.com/origin/3b0b000397e1e75251b0",
		"http://p1.pstatp.com/origin/3b0a00039e5aabdadc81",
		"http://p3.pstatp.com/origin/3b0a00039e647a7e546a",
		"http://p3.pstatp.com/origin/3b0a00039e5fee533dde"
	],
	"title" : "唐嫣用上海话祝胡歌生日快乐！",
	"url" : "http://toutiao.com/group/6467890145566654989/"
},
{
	"_id" : ObjectId("59f2c51e5bfbda3004aa51af"),
	"images_url" : [
		"http://p3.pstatp.com/origin/3b100001875c81592bd5",
		"http://p1.pstatp.com/origin/3b100001875f7999f32b",
		"http://p1.pstatp.com/origin/3b0b0003573792601a48",
		"http://p3.pstatp.com/origin/3b0c000355436d104632",
		"http://p3.pstatp.com/origin/3b0e00033cb836aa0d68",
		"http://p1.pstatp.com/origin/3b0e00033cbdd4adf77b",
		"http://p3.pstatp.com/origin/3b0c000355510a999a85"
	],
	"title" : "最近剧荒，期待胡歌的猎场，帅气登场",
	"url" : "http://toutiao.com/group/6467862574057652749/"
},
{
	"_id" : ObjectId("59f2c5215bfbda362ce3fe63"),
	"images_url" : [
		"http://p3.pstatp.com/origin/3afa0001b2a561f41ea1",
		"http://p9.pstatp.com/origin/3afb0001ab6c89619989",
		"http://p3.pstatp.com/origin/3a0900036fce749c1621",
		"http://p3.pstatp.com/origin/3a050003a4d729d1b67b",
		"http://p1.pstatp.com/origin/3a06000398d391a7cbe3",
		"http://p1.pstatp.com/origin/3a050003a4dd433dbad1",
		"http://p1.pstatp.com/origin/3a06000398da41deef92",
		"http://p3.pstatp.com/origin/3afa0001b2cc25b93d99"
	],
	"title" : "明星图集：琅琊榜 胡歌刘涛",
	"url" : "http://toutiao.com/group/6466190956679922189/"
},
{
	"_id" : ObjectId("59f2c5225bfbda0824dae755"),
	"images_url" : [
		"http://p3.pstatp.com/origin/31e700049531e3cf7d18",
		"http://p9.pstatp.com/origin/31e2000281d3d5879de4",
		"http://p3.pstatp.com/origin/31e2000281d5b0338944",
		"http://p3.pstatp.com/origin/31e00003fcdfbfd38100",
		"http://p3.pstatp.com/origin/31e00003fce394d701c9",
		"http://p3.pstatp.com/origin/31dc0003fe546e6c14ff",
		"http://p3.pstatp.com/origin/31df0004bd64800cec8c",
		"http://p3.pstatp.com/origin/31e50004ae75c31b6788",
		"http://p3.pstatp.com/origin/31e70004954d360f8393",
		"http://p1.pstatp.com/origin/31e00003fcee7ab65b52",
		"http://p1.pstatp.com/origin/31e70004954e07c7e000",
		"http://p3.pstatp.com/origin/31e70004954f5727fc1b",
		"http://p3.pstatp.com/origin/31e00003fcf16b174e34",
		"http://p1.pstatp.com/origin/31e50004ae7d7737a101",
		"http://p3.pstatp.com/origin/31df0004bd751d26e8fb"
	],
	"title" : "胡歌，帅出意境的美照",
	"url" : "http://toutiao.com/group/6449908897167130893/"
},
{
	"_id" : ObjectId("59f2c5225bfbda3b5429774a"),
	"images_url" : [
		"http://p3.pstatp.com/origin/321500009f923299c394",
		"http://p3.pstatp.com/origin/322c00027a77ecc5a362",
		"http://p1.pstatp.com/origin/321500009f968e482ff0",
		"http://p3.pstatp.com/origin/321500009f97a211de1b",
		"http://p3.pstatp.com/origin/3213000379ce98b27a91",
		"http://p3.pstatp.com/origin/321f0001a079c28fade5",
		"http://p3.pstatp.com/origin/321f0001a07c5cec639b",
		"http://p1.pstatp.com/origin/320c0001a2240f661275",
		"http://p9.pstatp.com/origin/322c00027a7e311e3a89"
	],
	"title" : "当胡歌遇上香奈儿……",
	"url" : "http://toutiao.com/group/6455193392140780046/"
},
{
	"_id" : ObjectId("59f2c52d5bfbda3004aa51b0"),
	"images_url" : [
		"http://p3.pstatp.com/origin/3b0d0000875b739e240c",
		"http://p1.pstatp.com/origin/3b0c0000894fdc69bbbb",
		"http://p1.pstatp.com/origin/3b0c000089152ad97b88",
		"http://p3.pstatp.com/origin/3b090003a709a081a590",
		"http://p1.pstatp.com/origin/3b090003a71715b2a47f",
		"http://p1.pstatp.com/origin/3b0e0000717ce03a8e09",
		"http://p3.pstatp.com/origin/3b0d00008773fb846337",
		"http://p3.pstatp.com/origin/3b0a00009199661dfcf1",
		"http://p9.pstatp.com/origin/3b080003b0b41012da36",
		"http://p1.pstatp.com/origin/3b0a000091a047d5cae3"
	],
	"title" : "高清壁纸 胡歌：娱乐圈中的一股清流",
	"url" : "http://toutiao.com/group/6467662742009430541/"
},
{
	"_id" : ObjectId("59f2c52d5bfbda3b5429774b"),
	"images_url" : [
		"http://p3.pstatp.com/origin/320b000213b2be584c5e",
		"http://p1.pstatp.com/origin/320b000213d80c14757f",
		"http://p3.pstatp.com/origin/32010002e7370eef4685",
		"http://p1.pstatp.com/origin/320b000213b715943b80",
		"http://p3.pstatp.com/origin/32140000c3eda172dfdb",
		"http://p1.pstatp.com/origin/32140000c3ea5d887747"
	],
	"title" : "娱乐圈有哪几个明星称得上钻石王老五，胡歌，彭于晏上榜",
	"url" : "http://toutiao.com/group/6452827771608498701/"
},
{
	"_id" : ObjectId("59f2c52e5bfbda0824dae756"),
	"images_url" : [
		"http://p1.pstatp.com/origin/1b870002f57a6dbdbf1d",
		"http://p3.pstatp.com/origin/1b870002f57bc70bb64e",
		"http://p9.pstatp.com/origin/1b8400030491bf7cf7d6",
		"http://p3.pstatp.com/origin/1b850002f6195217f992",
		"http://p3.pstatp.com/origin/1b82000311a81fcb4e7b",
		"http://p9.pstatp.com/origin/1b7f00061f9d259590e6",
		"http://p3.pstatp.com/origin/1b82000311ad8c5a1137",
		"http://p1.pstatp.com/origin/1b8100047915b1d6dd09",
		"http://p3.pstatp.com/origin/1b870002f582078f05b3"
	],
	"title" : "胡歌—你们要的老公！",
	"url" : "http://toutiao.com/group/6408833979440464129/"
},
{
	"_id" : ObjectId("59f2c5335bfbda3004aa51b1"),
	"images_url" : [
		"http://p1.pstatp.com/origin/39fb0004d9f1d12f33a6",
		"http://p3.pstatp.com/origin/39fd0003068926f9cdcf",
		"http://p3.pstatp.com/origin/39fe0002f47a0c1526f5",
		"http://p3.pstatp.com/origin/39f90004dec053467227",
		"http://p3.pstatp.com/origin/39fb0004da40d0f7a89f"
	],
	"title" : "胡歌抱猫爱心满满图集",
	"url" : "http://toutiao.com/group/6465110875387724301/"
},
{
	"_id" : ObjectId("59f2c5375bfbda3004aa51b2"),
	"images_url" : [
		"http://p3.pstatp.com/origin/39ab00052067bc44ec03",
		"http://p3.pstatp.com/origin/39ae00050664124aa1c3",
		"http://p1.pstatp.com/origin/39ac000503f26e395ec5",
		"http://p1.pstatp.com/origin/39af000503045f679673",
		"http://p3.pstatp.com/origin/39ac000503f389bca3b5",
		"http://p3.pstatp.com/origin/39b1000334d35da858e9"
	],
	"title" : "有多少人因为琅琊榜而更爱胡歌？",
	"url" : "http://toutiao.com/group/6463232054506045966/"
},
{
	"_id" : ObjectId("59f2c53d5bfbda3b5429774c"),
	"images_url" : [
		"http://p3.pstatp.com/origin/433400008e548bdf8b89",
		"http://p9.pstatp.com/origin/43320000a1c4002acb00",
		"http://p1.pstatp.com/origin/433400008e5ca740c31a",
		"http://p9.pstatp.com/origin/433400008e6106612432",
		"http://p1.pstatp.com/origin/43300002ede8d23269e5",
		"http://p3.pstatp.com/origin/43320000a1d03562f3e1",
		"http://p3.pstatp.com/origin/43310000adeb03364195",
		"http://p1.pstatp.com/origin/43300002edf2b7c16015"
	],
	"title" : "男粉丝比女粉丝多的男星，娱乐圈唯一一个毁了容还那么帅的男人！",
	"url" : "http://toutiao.com/group/6481128173206503950/"
},
{
	"_id" : ObjectId("59f2c5415bfbda3b5429774d"),
	"images_url" : [
		"http://p3.pstatp.com/origin/39b1000324808b6a3f29",
		"http://p3.pstatp.com/origin/39af0004f2e8407501e2",
		"http://p9.pstatp.com/origin/39b10003248259475523",
		"http://p3.pstatp.com/origin/39b200030055de004259",
		"http://p1.pstatp.com/origin/39b100032484a91f41b4",
		"http://p1.pstatp.com/origin/39b200030058d00349c9",
		"http://p1.pstatp.com/origin/39aa00050f1ff1c631d6"
	],
	"title" : "别人镜头下的胡歌，依旧帅的没渣！",
	"url" : "http://toutiao.com/group/6463228781799670286/"
},
{
	"_id" : ObjectId("59f2c5435bfbda3004aa51b3"),
	"images_url" : [
		"http://p3.pstatp.com/origin/402d000264f7e0e7a498",
		"http://p1.pstatp.com/origin/402e00025ba2d06707b9",
		"http://p3.pstatp.com/origin/402c00026df6db1d7155",
		"http://p3.pstatp.com/origin/402e00025bc33b44abd6",
		"http://p1.pstatp.com/origin/402f000108b6522ebc85",
		"http://p9.pstatp.com/origin/402c00026e1cf9aaca19",
		"http://p1.pstatp.com/origin/403100009c4987989768",
		"http://p3.pstatp.com/origin/402d000265478838168c",
		"http://p9.pstatp.com/origin/402c00026e38c3cbd1c2"
	],
	"title" : "胡歌图集 帅",
	"url" : "http://toutiao.com/group/6479561774881309198/"
},
{
	"_id" : ObjectId("59f2c5465bfbda0824dae757"),
	"images_url" : [
		"http://p3.pstatp.com/origin/16cc0003e5caa53acc1a",
		"http://p1.pstatp.com/origin/16d00002bea3a0401475",
		"http://p3.pstatp.com/origin/16cd0000889a87fb53bd",
		"http://p1.pstatp.com/origin/16cc0003e5d180b28eed",
		"http://p1.pstatp.com/origin/16cc0003e5d4aa3d9fbe",
		"http://p3.pstatp.com/origin/16c70001afd70c9582a8",
		"http://p3.pstatp.com/origin/16c80001d7228a417e1e"
	],
	"title" : "胡歌写真集",
	"url" : "http://toutiao.com/group/6388787288231952641/"
},
{
	"_id" : ObjectId("59f2c5465bfbda3b5429774e"),
	"images_url" : [
		"http://p3.pstatp.com/origin/320b000175ce70d8a7e0",
		"http://p3.pstatp.com/origin/320700006a787ae589b7",
		"http://p3.pstatp.com/origin/320700006b27b5df4265",
		"http://p3.pstatp.com/origin/31f60000bd004d776ef1",
		"http://p9.pstatp.com/origin/31f7000466b3132f3354",
		"http://p3.pstatp.com/origin/31fe00045ab402b4a887"
	],
	"title" : "胡歌，一个演员的基本素养",
	"url" : "http://toutiao.com/group/6452650055634518541/"
},
{
	"_id" : ObjectId("59f2c5495bfbda3b5429774f"),
	"images_url" : [
		"http://p3.pstatp.com/origin/37ec0000fbda7313b043",
		"http://p9.pstatp.com/origin/37ed0000f3429c14a0f6",
		"http://p1.pstatp.com/origin/37f10003ec42f815c8ed",
		"http://p1.pstatp.com/origin/37f20000ffb9a585f2c7",
		"http://p3.pstatp.com/origin/37f30000f3f09cefdbfa",
		"http://p1.pstatp.com/origin/37ec0000fc74f248fd31"
	],
	"title" : "胡歌穿衣有风格，不信你来看看",
	"url" : "http://toutiao.com/group/6461427730519949838/"
},
{
	"_id" : ObjectId("59f2c5495bfbda0824dae758"),
	"images_url" : [
		"http://p3.pstatp.com/origin/289300051c9b936c690b",
		"http://p3.pstatp.com/origin/28920001963a716fdc36",
		"http://p1.pstatp.com/origin/2899000000798de56328",
		"http://p1.pstatp.com/origin/28990000007873e71ff7",
		"http://p3.pstatp.com/origin/28950003830275231a40",
		"http://p1.pstatp.com/origin/2897000312488d5a9c86",
		"http://p3.pstatp.com/origin/2895000383059442e66e"
	],
	"title" : "好兄弟！胡歌靳东合照搞怪卖萌 胡歌搞笑翻白眼",
	"url" : "http://toutiao.com/group/6433633868246958338/"
},
{
	"_id" : ObjectId("59f2c54a5bfbda3004aa51b4"),
	"images_url" : [
		"http://p1.pstatp.com/origin/4332000077f1f2a3655e",
		"http://p3.pstatp.com/origin/432f0003541438753fd6",
		"http://p3.pstatp.com/origin/4335000059f4f71cf17e",
		"http://p1.pstatp.com/origin/432f000353b6bdf537ad"
	],
	"title" : "又一个假的“老干部“？口撕金星熊抱女主持，网友：莫装人设",
	"url" : "http://toutiao.com/group/6481116175316025870/"
},
{
	"_id" : ObjectId("59f2c54e5bfbda3004aa51b5"),
	"images_url" : [
		"http://p3.pstatp.com/origin/213e00044e3656865fa5",
		"http://p9.pstatp.com/origin/22d200034657c89a802f",
		"http://p3.pstatp.com/origin/213e00044ec665c84d88",
		"http://p1.pstatp.com/origin/213e000453c937271fe8",
		"http://p1.pstatp.com/origin/22d60003ecf161fbf27b",
		"http://p3.pstatp.com/origin/22d2000346739a61c710"
	],
	"title" : "最帅男明星排行榜：胡歌居然垫底",
	"url" : "http://toutiao.com/group/6425534848622952706/"
},
{
	"_id" : ObjectId("59f2c5515bfbda362ce3fe64"),
	"images_url" : [
		"http://p3.pstatp.com/origin/3c6b0003f7fcef823095",
		"http://p1.pstatp.com/origin/3c6500021ab4923dabe6",
		"http://p3.pstatp.com/origin/3c6a0003d318a27ea140",
		"http://p3.pstatp.com/origin/3c6c000218b412ecf8b6",
		"http://p1.pstatp.com/origin/3c6a0003d357368787d2",
		"http://p9.pstatp.com/origin/3c690003f56fc5740d57",
		"http://p3.pstatp.com/origin/3c6c0002184673d3eb91",
		"http://p3.pstatp.com/origin/3c6500021b5376fd42f8"
	],
	"title" : "明星图集：刘诗诗 胡歌",
	"url" : "http://toutiao.com/group/6470267681797833230/"
},
{
	"_id" : ObjectId("59f2c5535bfbda3004aa51b6"),
	"images_url" : [
		"http://p9.pstatp.com/origin/17f30002296ca9f85e1c",
		"http://p9.pstatp.com/origin/17f30002297dedc56dce",
		"http://p3.pstatp.com/origin/16ce0003cf58ad057d0f"
	],
	"title" : "胡歌再度获奖，临别前夕，泪洒现场！",
	"url" : "http://toutiao.com/group/6391449395061883138/"
},
{
	"_id" : ObjectId("59f2c5575bfbda3b54297750"),
	"images_url" : [
		"http://p9.pstatp.com/origin/31f00002be6cae7a60ed",
		"http://p9.pstatp.com/origin/31eb0005092e00e439d0",
		"http://p1.pstatp.com/origin/31e9000428d4b140a2c2",
		"http://p1.pstatp.com/origin/31eb00050934589aa55d",
		"http://p1.pstatp.com/origin/31f400044b9189a94cb0",
		"http://p3.pstatp.com/origin/31ed0002c0ea8b5251cb",
		"http://p3.pstatp.com/origin/31e60005078a210233ef",
		"http://p3.pstatp.com/origin/31ed0002c0f0670353ba",
		"http://p3.pstatp.com/origin/31e60005078ef5f66fe4"
	],
	"title" : "实力演员胡歌帅气逼人写真",
	"url" : "http://toutiao.com/group/6451354980716839182/"
},
{
	"_id" : ObjectId("59f2c5595bfbda3004aa51b7"),
	"images_url" : [
		"http://p3.pstatp.com/origin/289300051c9b936c690b",
		"http://p3.pstatp.com/origin/28920001963a716fdc36",
		"http://p1.pstatp.com/origin/2899000000798de56328",
		"http://p1.pstatp.com/origin/28990000007873e71ff7",
		"http://p3.pstatp.com/origin/28950003830275231a40",
		"http://p1.pstatp.com/origin/2897000312488d5a9c86",
		"http://p3.pstatp.com/origin/2895000383059442e66e"
	],
	"title" : "好兄弟！胡歌靳东合照搞怪卖萌 胡歌搞笑翻白眼",
	"url" : "http://toutiao.com/group/6433633868246958338/"
},
{
	"_id" : ObjectId("59f2c55a5bfbda0824dae759"),
	"images_url" : [
		"http://p1.pstatp.com/origin/e8f00019b49a6b1be5e",
		"http://p1.pstatp.com/origin/e8f00019b4b2afe5d3b",
		"http://p3.pstatp.com/origin/e90000199338ef0b275",
		"http://p3.pstatp.com/origin/e9200019955a2464f3e",
		"http://p3.pstatp.com/origin/ddf000553631eb4c613",
		"http://p9.pstatp.com/origin/e8e00019a0f5db8807e",
		"http://p3.pstatp.com/origin/e9200019938ad7ab6e8",
		"http://p9.pstatp.com/origin/e9000019938ee36b2b5",
		"http://p1.pstatp.com/origin/e8f00019b4e87f589ad",
		"http://p1.pstatp.com/origin/ddf0005537228b9c89c",
		"http://p9.pstatp.com/origin/e8f00019b595ca68fc6",
		"http://p3.pstatp.com/origin/e900001993ffce30450",
		"http://p3.pstatp.com/origin/e900001994356ddd380",
		"http://p3.pstatp.com/origin/e8f00019b574806d911",
		"http://p1.pstatp.com/origin/e9200019946794f4bb4",
		"http://p9.pstatp.com/origin/e90000199489e6d23cf",
		"http://p1.pstatp.com/origin/ddf0005537a226fb471",
		"http://p1.pstatp.com/origin/e8f00019b5bd4b00c66",
		"http://p1.pstatp.com/origin/e900001994de24fc262"
	],
	"title" : "胡歌生日快乐",
	"url" : "http://toutiao.com/group/6332069302464545026/"
},
{
	"_id" : ObjectId("59f2c55c5bfbda0824dae75a"),
	"images_url" : [
		"http://p1.pstatp.com/origin/2ec100035f5558399a48",
		"http://p1.pstatp.com/origin/2ecc00036178e6f0d597",
		"http://p3.pstatp.com/origin/2eca0001d44967197ff6",
		"http://p1.pstatp.com/origin/2ed00001bfda4582b69a",
		"http://p1.pstatp.com/origin/2ecc000361851d64d3c5"
	],
	"title" : "胡歌就是帅啊",
	"url" : "http://toutiao.com/group/6442632967738851585/"
},
{
	"_id" : ObjectId("59f2c55d5bfbda3b54297751"),
	"images_url" : [
		"http://p3.pstatp.com/origin/404200044e01adea14bc",
		"http://p3.pstatp.com/origin/40410004614306d7bc6f",
		"http://p3.pstatp.com/origin/40410004614b223b37b6",
		"http://p3.pstatp.com/origin/43310000058480175870",
		"http://p1.pstatp.com/origin/432f0002d6f4518d6c75"
	],
	"title" : "19岁出道，奥运冠军的表妹，《伪装者》里本是配角却演成了主角",
	"url" : "http://toutiao.com/group/6481091607494918669/"
},
{
	"_id" : ObjectId("59f2c5635bfbda362ce3fe65"),
	"images_url" : [
		"http://p3.pstatp.com/origin/3afb00032fc651c4a685",
		"http://p9.pstatp.com/origin/3b0000001792efb6886a",
		"http://p1.pstatp.com/origin/3b0000001795526fabf9",
		"http://p1.pstatp.com/origin/3b0000001793fd959246",
		"http://p3.pstatp.com/origin/3b0000001794d6ea7e2f",
		"http://p9.pstatp.com/origin/3afc0000415135c0a5a1",
		"http://p1.pstatp.com/origin/3aff00002d7a5dfbe48c",
		"http://p1.pstatp.com/origin/3b00000017e7601b3e65",
		"http://p3.pstatp.com/origin/3b00000017e53dbd2de9",
		"http://p1.pstatp.com/origin/3afb0003300a09fd2983"
	],
	"title" : "我大胡歌就是那么帅，你吹吗",
	"url" : "http://toutiao.com/group/6466342261817868814/"
},
{
	"_id" : ObjectId("59f2c5655bfbda0824dae75b"),
	"images_url" : [
		"http://p3.pstatp.com/origin/b0f00079260a256d67f",
		"http://p1.pstatp.com/origin/b9d00003418c408ff28",
		"http://p1.pstatp.com/origin/b9d000034039b43598c",
		"http://p1.pstatp.com/origin/b0f000792676bbf4c1d",
		"http://p3.pstatp.com/origin/b9d0000340e7d6159e1",
		"http://p1.pstatp.com/origin/b9d00003416b44c04be",
		"http://p1.pstatp.com/origin/b9d000034172fb91a4f",
		"http://p1.pstatp.com/origin/b0f00079250aedc828e",
		"http://p3.pstatp.com/origin/b9e0000345cf3fc7d55"
	],
	"title" : "霍建华紧握胡歌手，胡歌“生无可恋”",
	"url" : "http://toutiao.com/group/6313145068171067649/"
},
{
	"_id" : ObjectId("59f2c5655bfbda3004aa51b8"),
	"images_url" : [
		"http://p1.pstatp.com/origin/e8f00019b49a6b1be5e",
		"http://p1.pstatp.com/origin/e8f00019b4b2afe5d3b",
		"http://p3.pstatp.com/origin/e90000199338ef0b275",
		"http://p3.pstatp.com/origin/e9200019955a2464f3e",
		"http://p3.pstatp.com/origin/ddf000553631eb4c613",
		"http://p9.pstatp.com/origin/e8e00019a0f5db8807e",
		"http://p3.pstatp.com/origin/e9200019938ad7ab6e8",
		"http://p9.pstatp.com/origin/e9000019938ee36b2b5",
		"http://p1.pstatp.com/origin/e8f00019b4e87f589ad",
		"http://p1.pstatp.com/origin/ddf0005537228b9c89c",
		"http://p9.pstatp.com/origin/e8f00019b595ca68fc6",
		"http://p3.pstatp.com/origin/e900001993ffce30450",
		"http://p3.pstatp.com/origin/e900001994356ddd380",
		"http://p3.pstatp.com/origin/e8f00019b574806d911",
		"http://p1.pstatp.com/origin/e9200019946794f4bb4",
		"http://p9.pstatp.com/origin/e90000199489e6d23cf",
		"http://p1.pstatp.com/origin/ddf0005537a226fb471",
		"http://p1.pstatp.com/origin/e8f00019b5bd4b00c66",
		"http://p1.pstatp.com/origin/e900001994de24fc262"
	],
	"title" : "胡歌生日快乐",
	"url" : "http://toutiao.com/group/6332069302464545026/"
},
{
	"_id" : ObjectId("59f2c5675bfbda3004aa51b9"),
	"images_url" : [
		"http://p1.pstatp.com/origin/2ec100035f5558399a48",
		"http://p1.pstatp.com/origin/2ecc00036178e6f0d597",
		"http://p3.pstatp.com/origin/2eca0001d44967197ff6",
		"http://p1.pstatp.com/origin/2ed00001bfda4582b69a",
		"http://p1.pstatp.com/origin/2ecc000361851d64d3c5"
	],
	"title" : "胡歌就是帅啊",
	"url" : "http://toutiao.com/group/6442632967738851585/"
},
{
	"_id" : ObjectId("59f2c5695bfbda362ce3fe66"),
	"images_url" : [
		"http://p3.pstatp.com/origin/3b0d000310dc85ea13f8",
		"http://p1.pstatp.com/origin/3b0e0002fb7707a9c106",
		"http://p3.pstatp.com/origin/3b100001457877b7476f",
		"http://p9.pstatp.com/origin/3b0e0002fb8256996354",
		"http://p3.pstatp.com/origin/3b0b000316c53913c554",
		"http://p3.pstatp.com/origin/3b0e0002fb870037b2b2",
		"http://p1.pstatp.com/origin/3b0e0002fb8bd209c072",
		"http://p3.pstatp.com/origin/3b0c000314b7ddc15e6a"
	],
	"title" : "十年蜕变，造就演员胡歌 老胡生日快乐！",
	"url" : "http://toutiao.com/group/6467842050833252877/"
},
{
	"_id" : ObjectId("59f2c56c5bfbda3004aa51ba"),
	"images_url" : [
		"http://p3.pstatp.com/origin/b0f00079260a256d67f",
		"http://p1.pstatp.com/origin/b9d00003418c408ff28",
		"http://p1.pstatp.com/origin/b9d000034039b43598c",
		"http://p1.pstatp.com/origin/b0f000792676bbf4c1d",
		"http://p3.pstatp.com/origin/b9d0000340e7d6159e1",
		"http://p1.pstatp.com/origin/b9d00003416b44c04be",
		"http://p1.pstatp.com/origin/b9d000034172fb91a4f",
		"http://p1.pstatp.com/origin/b0f00079250aedc828e",
		"http://p3.pstatp.com/origin/b9e0000345cf3fc7d55"
	],
	"title" : "霍建华紧握胡歌手，胡歌“生无可恋”",
	"url" : "http://toutiao.com/group/6313145068171067649/"
},
{
	"_id" : ObjectId("59f2c56c5bfbda362ce3fe67"),
	"images_url" : [
		"http://p3.pstatp.com/origin/37e3000256bf14932835",
		"http://p9.pstatp.com/origin/37e7000066cfb703881c",
		"http://p3.pstatp.com/origin/37e7000066cd483b10e5",
		"http://p3.pstatp.com/origin/37e7000066ce74a4e9ff",
		"http://p3.pstatp.com/origin/37de000247e1ec1d054a",
		"http://p1.pstatp.com/origin/37e600023f8b55fce101",
		"http://p1.pstatp.com/origin/37e500024943bdbda682"
	],
	"title" : "胡歌实力派 精彩美图来袭",
	"url" : "http://toutiao.com/group/6460190126088651277/"
},
{
	"_id" : ObjectId("59f2c5715bfbda3004aa51bb"),
	"images_url" : [
		"http://p9.pstatp.com/origin/26e50003876af7401e53",
		"http://p9.pstatp.com/origin/26e0000432719ea8f41d",
		"http://p3.pstatp.com/origin/26ea00003d92a3bc2c10",
		"http://p3.pstatp.com/origin/26e50003876cf87b44a2",
		"http://p3.pstatp.com/origin/26ea00003d979f16da16",
		"http://p1.pstatp.com/origin/26e50003876ebdae2c25"
	],
	"title" : "胡歌，我们的最爱",
	"url" : "http://toutiao.com/group/6430323277777174786/"
},
{
	"_id" : ObjectId("59f2c57a5bfbda3004aa51bc"),
	"images_url" : [
		"http://p3.pstatp.com/origin/12d9000439a474899257",
		"http://p1.pstatp.com/origin/12d70002a5eb2af21afd",
		"http://p1.pstatp.com/origin/12dc00032813fdb3ca64",
		"http://p1.pstatp.com/origin/12d80005b23a40372607",
		"http://p9.pstatp.com/origin/12d6000260124bdc5c2d",
		"http://p3.pstatp.com/origin/12dc0003284648407a8c",
		"http://p3.pstatp.com/origin/12d70002a66eaa2a9db0",
		"http://p1.pstatp.com/origin/12dc000328915e02e7e8",
		"http://p3.pstatp.com/origin/12d900043dc641acf653",
		"http://p1.pstatp.com/origin/12d80005b5e63e33a3d7"
	],
	"title" : "“不变的胡歌”",
	"url" : "http://toutiao.com/group/6362490222504476930/"
},
{
	"_id" : ObjectId("59f2c5815bfbda3004aa51bd"),
	"images_url" : [
		"http://p3.pstatp.com/origin/26f10002fe5c56dbbf0b",
		"http://p3.pstatp.com/origin/26eb00058c3ca7fb5303",
		"http://p3.pstatp.com/origin/26eb00058c3fb338d59c",
		"http://p3.pstatp.com/origin/26f0000300d97e5839ce",
		"http://p3.pstatp.com/origin/26ee000396414bf28021",
		"http://p1.pstatp.com/origin/26ed0005839bda8c5f74",
		"http://p3.pstatp.com/origin/26eb00058c437953f586",
		"http://p1.pstatp.com/origin/26eb00058c412fd96d9a"
	],
	"title" : "胡歌代言荣耀9，当帅遇上帅",
	"url" : "http://toutiao.com/item/6431118822245138945/"
},
{
	"_id" : ObjectId("59f2c5845bfbda3004aa51be"),
	"images_url" : [
		"http://p9.pstatp.com/origin/c5e0004148a27b23696",
		"http://p3.pstatp.com/origin/ca20000f1e1b12834bb",
		"http://p3.pstatp.com/origin/c5b00073f75c79524ba",
		"http://p1.pstatp.com/origin/c5e0004148938ecc569",
		"http://p1.pstatp.com/origin/c12000492cd2eb1a346",
		"http://p3.pstatp.com/origin/c5d00074792cf53a5e5",
		"http://p3.pstatp.com/origin/ca20000f1e90ae3b367"
	],
	"title" : "胡歌，人生如歌，帅呆了",
	"url" : "http://toutiao.com/group/6320561132277317890/"
},
{
	"_id" : ObjectId("59f2c58c5bfbda3004aa51bf"),
	"images_url" : [
		"http://p1.pstatp.com/origin/9de0000f5e28cee4262",
		"http://p3.pstatp.com/origin/9e100015f5f71956971",
		"http://p3.pstatp.com/origin/96f00097d5b26bf2521",
		"http://p1.pstatp.com/origin/96f00097d5cfe6e3275",
		"http://p1.pstatp.com/origin/9df000102fe6f7d9293",
		"http://p3.pstatp.com/origin/9de0000f5e329f2b018",
		"http://p1.pstatp.com/origin/9de0000f5e4bc12b361",
		"http://p1.pstatp.com/origin/9aa0002e5cf9c1d4774"
	],
	"title" : "胡歌米兰街拍大片",
	"url" : "http://toutiao.com/group/6303212177294393601/"
},
{
	"_id" : ObjectId("59f2c5955bfbda3004aa51c0"),
	"images_url" : [
		"http://p3.pstatp.com/origin/a770004a996bb27a4aa",
		"http://p3.pstatp.com/origin/a780004a5cbdad4bbf0",
		"http://p3.pstatp.com/origin/a770004aafce32735db",
		"http://p1.pstatp.com/origin/a770004ab736942a08e",
		"http://p1.pstatp.com/origin/a770004abf89f72772b",
		"http://p1.pstatp.com/origin/a770004ac476ff2cb98",
		"http://p3.pstatp.com/origin/a780004a86b976fbbc1",
		"http://p1.pstatp.com/origin/a780004a8eeb4f5b6be",
		"http://p1.pstatp.com/origin/a770004adbb95a426a1",
		"http://p3.pstatp.com/origin/a770004ae2030fe6b44",
		"http://p1.pstatp.com/origin/a780004aaf1181fbf1e",
		"http://p1.pstatp.com/origin/a770004af951f81f7b1",
		"http://p3.pstatp.com/origin/a770004afca2dcb94e3",
		"http://p1.pstatp.com/origin/a790004a92dd96d2866",
		"http://p1.pstatp.com/origin/a770004b0defa5ca8f0",
		"http://p3.pstatp.com/origin/a780004ad6788ebfa79",
		"http://p3.pstatp.com/origin/a780004adcf6b303630",
		"http://p3.pstatp.com/origin/a770004b28967d66020"
	],
	"title" : "胡歌新剧《猎场》和大批男神飙戏！",
	"url" : "http://toutiao.com/group/6289926241831780609/"
},
{
	"_id" : ObjectId("59f2c5995bfbda3004aa51c1"),
	"images_url" : [
		"http://p3.pstatp.com/origin/1090000174086cd24be",
		"http://p3.pstatp.com/origin/109000017429cb5742f",
		"http://p3.pstatp.com/origin/10a000017013228b850",
		"http://p3.pstatp.com/origin/1090000174393c9ac7a",
		"http://p3.pstatp.com/origin/10a0000170ab8e5bf56",
		"http://p1.pstatp.com/origin/cd0007a75ac1d0a500",
		"http://p1.pstatp.com/origin/10a0000170dbd652adc",
		"http://p3.pstatp.com/origin/ce0007a7984abf9496"
	],
	"title" : "胡歌拍戏时居然喜欢玩这个！",
	"url" : "http://toutiao.com/group/6244237990450970882/"
},
{
	"_id" : ObjectId("59f2c59f5bfbda3004aa51c2"),
	"images_url" : [
		"http://p3.pstatp.com/origin/15350005d783ac2b7cf7",
		"http://p1.pstatp.com/origin/15350005d784d3df71cc",
		"http://p3.pstatp.com/origin/15330005ef4a5f28a5da",
		"http://p3.pstatp.com/origin/15330005ef4ef18e12c5",
		"http://p1.pstatp.com/origin/15360003402bbb8b9711",
		"http://p1.pstatp.com/origin/153800032fd0c184c6cd"
	],
	"title" : "胡歌的阿玛尼广告大片",
	"url" : "http://toutiao.com/group/6374746118069043458/"
},
{
	"_id" : ObjectId("59f2c5a45bfbda3004aa51c3"),
	"images_url" : [
		"http://p1.pstatp.com/origin/d010008c35886bd650c",
		"http://p1.pstatp.com/origin/d020006116eed129451",
		"http://p3.pstatp.com/origin/d000006196c8eef927e",
		"http://p3.pstatp.com/origin/d020006117166ebb85d",
		"http://p3.pstatp.com/origin/d030004bce8dbf969a0",
		"http://p1.pstatp.com/origin/d0500007376c805ab74",
		"http://p3.pstatp.com/origin/d0200061178c2543dd0",
		"http://p3.pstatp.com/origin/d000006197b9af8ab66",
		"http://p3.pstatp.com/origin/d000006197c448152ea"
	],
	"title" : "胡歌最新大片：尽显轻熟男本色",
	"url" : "http://toutiao.com/group/6325736221521215745/"
},
{
	"_id" : ObjectId("59f2c5ab5bfbda3004aa51c4"),
	"images_url" : [
		"http://p3.pstatp.com/origin/19fa00058f110aa866eb",
		"http://p1.pstatp.com/origin/19f60003c9b5b6f1677d",
		"http://p3.pstatp.com/origin/19fa00058f2554b5cb84",
		"http://p3.pstatp.com/origin/19fe0003cbba0f831330",
		"http://p3.pstatp.com/origin/19fc0003c2b009e4f9e9",
		"http://p3.pstatp.com/origin/19f60003c9d906fa41e6",
		"http://p1.pstatp.com/origin/19ff0003ba94e55db72a",
		"http://p1.pstatp.com/origin/19ff0003ba9710fd6f5f",
		"http://p1.pstatp.com/origin/19fe0003cbcf83119a7b"
	],
	"title" : "胡歌前女友江疏影，不一样的美女",
	"url" : "http://toutiao.com/group/6405325015604855041/"
},
{
	"_id" : ObjectId("59f2c5b55bfbda3004aa51c5"),
	"images_url" : [
		"http://p1.pstatp.com/origin/96d00042692fd5f0644",
		"http://p1.pstatp.com/origin/96e00042301e302f37b",
		"http://p3.pstatp.com/origin/9700002ac6beeedb3b8",
		"http://p3.pstatp.com/origin/96c0002aadedd59b11a",
		"http://p1.pstatp.com/origin/9700002acce560d772a",
		"http://p3.pstatp.com/origin/96d0004270bfb934d4e",
		"http://p3.pstatp.com/origin/96c0002ae70ecd9cb7c",
		"http://p1.pstatp.com/origin/96f00012c93124cb763",
		"http://p3.pstatp.com/origin/96e000427c7c8301441",
		"http://p3.pstatp.com/origin/96f00012efcd019b32b",
		"http://p1.pstatp.com/origin/96e00042f7e7f6a067e",
		"http://p3.pstatp.com/origin/96d00042c505c4f0a08",
		"http://p3.pstatp.com/origin/96c0002b08a874789ec",
		"http://p3.pstatp.com/origin/96e00042c4530d20137",
		"http://p1.pstatp.com/origin/9700002b4f89e5b3b44",
		"http://p3.pstatp.com/origin/9700002b525111eb947",
		"http://p1.pstatp.com/origin/96f000131ead791490d",
		"http://p3.pstatp.com/origin/9700002b532cc41330f",
		"http://p3.pstatp.com/origin/96f0001324a3804ee0b",
		"http://p3.pstatp.com/origin/96c0002b506c4b6f692",
		"http://p1.pstatp.com/origin/9e10005a78fe94ee765",
		"http://p3.pstatp.com/origin/96d00043041bc86adf1",
		"http://p1.pstatp.com/origin/96d000431ae073097e0",
		"http://p1.pstatp.com/origin/96c0002b5f65fa75bf6",
		"http://p3.pstatp.com/origin/9e00005b48bfb586ac7",
		"http://p3.pstatp.com/origin/9de000547e779417759",
		"http://p3.pstatp.com/origin/9de000547b8f67e920e",
		"http://p3.pstatp.com/origin/9e00005b4cba0ed98ab",
		"http://p3.pstatp.com/origin/9e00005c7a17fba5967",
		"http://p3.pstatp.com/origin/9e00005c7c07cdd190f",
		"http://p3.pstatp.com/origin/9e10005c2716cae06ef",
		"http://p1.pstatp.com/origin/9aa0007349a97359cbe",
		"http://p1.pstatp.com/origin/9e10005bfe9e606b775"
	],
	"title" : "胡歌那不为人知的一面",
	"url" : "http://toutiao.com/group/6306747865666765057/"
},
{
	"_id" : ObjectId("59f2c5bf5bfbda3004aa51c6"),
	"images_url" : [
		"http://p3.pstatp.com/origin/3e4000a4e57085e8f7a",
		"http://p1.pstatp.com/origin/485000016f5a8b553e0",
		"http://p1.pstatp.com/origin/3e7000a4b1fd9cb7fe1",
		"http://p3.pstatp.com/origin/3e7000a4b2c6138b200",
		"http://p3.pstatp.com/origin/48500001700c41630f9"
	],
	"title" : "胡歌最新帅气写真新鲜出炉！",
	"url" : "http://toutiao.com/group/6270290654803378433/"
},
